pytopsort/__init__.py
pytopsort-1.0.0.dist-info/LICENSE
pytopsort-1.0.0.dist-info/WHEEL
pytopsort-1.0.0.dist-info/METADATA
pytopsort-1.0.0.dist-info/RECORD
