Metadata-Version: 2.1
Name: pytopsort
Version: 1.0.0
Summary: Python implementation of topological sort
License: MIT
Author: Pavel Kulyov
Author-email: kulyov.pavel@gmail.com
Requires-Python: >=3.6,<4.0
Classifier: License :: OSI Approved :: MIT License
Classifier: Programming Language :: Python :: 3
Classifier: Programming Language :: Python :: 3.6
Classifier: Programming Language :: Python :: 3.7
Classifier: Programming Language :: Python :: 3.8
